{
	"Version": 3,
	"Meta": {
		"Duration": 4.667,
		"Fps": 30.0,
		"Loop": true,
		"AreBeziersRestricted": true,
		"CurveCount": 80,
		"TotalSegmentCount": 331,
		"TotalPointCount": 983,
		"UserDataCount": 0,
		"TotalUserDataSize": 0
	},
	"Curves": [
		{
			"Target": "Parameter",
			"Id": "Param55",
			"Segments": [
				0,
				0,
				1,
				1.556,
				0,
				3.111,
				0,
				4.667,
				0
			]
		},
		{
			"Target": "Parameter",
			"Id": "Param56",
			"Segments": [
				0,
				0,
				1,
				1.556,
				0,
				3.111,
				0,
				4.667,
				0
			]
		},
		{
			"Target": "Parameter",
			"Id": "Param57",
			"Segments": [
				0,
				0,
				1,
				1.556,
				0,
				3.111,
				0,
				4.667,
				0
			]
		},
		{
			"Target": "Parameter",
			"Id": "Param58",
			"Segments": [
				0,
				0,
				1,
				1.556,
				0,
				3.111,
				0,
				4.667,
				0
			]
		},
		{
			"Target": "Parameter",
			"Id": "Param59",
			"Segments": [
				0,
				0,
				1,
				1.556,
				0,
				3.111,
				0,
				4.667,
				0
			]
		},
		{
			"Target": "Parameter",
			"Id": "Param25",
			"Segments": [
				0,
				1,
				1,
				1.556,
				1,
				3.111,
				1,
				4.667,
				1
			]
		},
		{
			"Target": "Parameter",
			"Id": "Param",
			"Segments": [
				0,
				0,
				1,
				1.556,
				0,
				3.111,
				0,
				4.667,
				0
			]
		},
		{
			"Target": "Parameter",
			"Id": "ParamLookAngleX",
			"Segments": [
				0,
				0,
				1,
				0.722,
				0,
				1.444,
				0,
				2.167,
				0,
				1,
				2.356,
				0,
				2.544,
				5,
				2.733,
				5,
				1,
				3.178,
				5,
				3.622,
				5,
				4.067,
				5,
				1,
				4.267,
				5,
				4.467,
				0,
				4.667,
				0
			]
		},
		{
			"Target": "Parameter",
			"Id": "ParamLookAngleY",
			"Segments": [
				0,
				-0.832,
				1,
				0.078,
				-0.832,
				0.156,
				-5,
				0.233,
				-5,
				1,
				0.3,
				-5,
				0.367,
				13,
				0.433,
				13,
				1,
				0.5,
				13,
				0.567,
				-3,
				0.633,
				-3,
				1,
				0.7,
				-3,
				0.767,
				5,
				0.833,
				5,
				1,
				0.889,
				5,
				0.944,
				5,
				1,
				5,
				1,
				1.178,
				5,
				1.356,
				-5,
				1.533,
				-5,
				1,
				1.7,
				-5,
				1.867,
				0,
				2.033,
				0,
				1,
				2.222,
				0,
				2.411,
				-30,
				2.6,
				-30,
				1,
				2.922,
				-30,
				3.244,
				-20,
				3.567,
				-20,
				1,
				3.689,
				-20,
				3.811,
				-30,
				3.933,
				-30,
				1,
				4.178,
				-30,
				4.422,
				-0.832,
				4.667,
				-0.832
			]
		},
		{
			"Target": "Parameter",
			"Id": "ParamAngleZ",
			"Segments": [
				0,
				3.892,
				1,
				0.022,
				3.892,
				0.044,
				3.892,
				0.067,
				3.892,
				1,
				0.144,
				3.892,
				0.222,
				20,
				0.3,
				20,
				1,
				0.444,
				20,
				0.589,
				20,
				0.733,
				20,
				1,
				1.022,
				20,
				1.311,
				3.892,
				1.6,
				3.892,
				1,
				1.778,
				3.892,
				1.956,
				22,
				2.133,
				22,
				1,
				2.322,
				22,
				2.511,
				10,
				2.7,
				10,
				1,
				2.878,
				10,
				3.056,
				15,
				3.233,
				15,
				1,
				3.511,
				15,
				3.789,
				15,
				4.067,
				15,
				1,
				4.267,
				15,
				4.467,
				3.892,
				4.667,
				3.892
			]
		},
		{
			"Target": "Parameter",
			"Id": "Param38",
			"Segments": [
				0,
				0,
				1,
				1.556,
				0,
				3.111,
				0,
				4.667,
				0
			]
		},
		{
			"Target": "Parameter",
			"Id": "Param2",
			"Segments": [
				0,
				0,
				1,
				0.056,
				0,
				0.111,
				-1,
				0.167,
				-1,
				1,
				1.422,
				-1,
				2.678,
				-1,
				3.933,
				-1,
				1,
				4.178,
				-1,
				4.422,
				0,
				4.667,
				0
			]
		},
		{
			"Target": "Parameter",
			"Id": "ParamEyeLOpen",
			"Segments": [
				0,
				1,
				1,
				0.133,
				1,
				0.267,
				1.1,
				0.4,
				1.1,
				1,
				0.778,
				1.1,
				1.156,
				1,
				1.533,
				1,
				1,
				1.589,
				1,
				1.644,
				1,
				1.7,
				1,
				1,
				1.789,
				1,
				1.878,
				0,
				1.967,
				0,
				1,
				2.044,
				0,
				2.122,
				1,
				2.2,
				1,
				1,
				2.344,
				1,
				2.489,
				0.7,
				2.633,
				0.7,
				1,
				2.833,
				0.7,
				3.033,
				0.8,
				3.233,
				0.8,
				1,
				3.467,
				0.8,
				3.7,
				0.8,
				3.933,
				0.8,
				1,
				4.056,
				0.8,
				4.178,
				0,
				4.3,
				0,
				1,
				4.422,
				0,
				4.544,
				1,
				4.667,
				1
			]
		},
		{
			"Target": "Parameter",
			"Id": "ParamEyeLSmile",
			"Segments": [
				0,
				0,
				1,
				1.311,
				0,
				2.622,
				0,
				3.933,
				0,
				1,
				4.178,
				0,
				4.422,
				0,
				4.667,
				0
			]
		},
		{
			"Target": "Parameter",
			"Id": "ParamEyeROpen",
			"Segments": [
				0,
				1,
				1,
				0.133,
				1,
				0.267,
				1.1,
				0.4,
				1.1,
				1,
				0.778,
				1.1,
				1.156,
				1,
				1.533,
				1,
				1,
				1.589,
				1,
				1.644,
				1,
				1.7,
				1,
				1,
				1.789,
				1,
				1.878,
				0,
				1.967,
				0,
				1,
				2.044,
				0,
				2.122,
				1,
				2.2,
				1,
				1,
				2.344,
				1,
				2.489,
				0.7,
				2.633,
				0.7,
				1,
				2.833,
				0.7,
				3.033,
				0.8,
				3.233,
				0.8,
				1,
				3.467,
				0.8,
				3.7,
				0.8,
				3.933,
				0.8,
				1,
				4.056,
				0.8,
				4.178,
				0,
				4.3,
				0,
				1,
				4.422,
				0,
				4.544,
				1,
				4.667,
				1
			]
		},
		{
			"Target": "Parameter",
			"Id": "ParamEyeRSmile",
			"Segments": [
				0,
				0,
				1,
				1.556,
				0,
				3.111,
				0,
				4.667,
				0
			]
		},
		{
			"Target": "Parameter",
			"Id": "Param3",
			"Segments": [
				0,
				1,
				1,
				1.556,
				1,
				3.111,
				1,
				4.667,
				1
			]
		},
		{
			"Target": "Parameter",
			"Id": "ParamLookEyeBallX",
			"Segments": [
				0,
				0,
				1,
				0.722,
				0,
				1.444,
				0,
				2.167,
				0,
				1,
				2.311,
				0,
				2.456,
				-0.6,
				2.6,
				-0.6,
				1,
				2.8,
				-0.6,
				3,
				-0.4,
				3.2,
				-0.4,
				1,
				3.389,
				-0.4,
				3.578,
				-0.4,
				3.767,
				-0.4,
				1,
				3.867,
				-0.4,
				3.967,
				0,
				4.067,
				0,
				1,
				4.267,
				0,
				4.467,
				0,
				4.667,
				0
			]
		},
		{
			"Target": "Parameter",
			"Id": "ParamLookEyeBallY",
			"Segments": [
				0,
				0,
				1,
				0.089,
				0,
				0.178,
				-0.3,
				0.267,
				-0.3,
				1,
				0.344,
				-0.3,
				0.422,
				0.4,
				0.5,
				0.4,
				1,
				0.578,
				0.4,
				0.656,
				-0.2,
				0.733,
				-0.2,
				1,
				0.822,
				-0.2,
				0.911,
				0.1,
				1,
				0.1,
				1,
				1.178,
				0.1,
				1.356,
				0,
				1.533,
				0,
				1,
				1.6,
				0,
				1.667,
				0,
				1.733,
				0,
				1,
				1.811,
				0,
				1.889,
				-0.5,
				1.967,
				-0.5,
				1,
				2.033,
				-0.5,
				2.1,
				0,
				2.167,
				0,
				1,
				2.311,
				0,
				2.456,
				0,
				2.6,
				0,
				1,
				2.8,
				0,
				3,
				-0.5,
				3.2,
				-0.5,
				1,
				3.567,
				-0.5,
				3.933,
				-0.5,
				4.3,
				-0.5,
				1,
				4.422,
				-0.5,
				4.544,
				0,
				4.667,
				0
			]
		},
		{
			"Target": "Parameter",
			"Id": "ParamBrowLY",
			"Segments": [
				0,
				0,
				1,
				1.556,
				0,
				3.111,
				0,
				4.667,
				0
			]
		},
		{
			"Target": "Parameter",
			"Id": "ParamBrowRY",
			"Segments": [
				0,
				0,
				1,
				1.556,
				0,
				3.111,
				0,
				4.667,
				0
			]
		},
		{
			"Target": "Parameter",
			"Id": "ParamBrowLAngle",
			"Segments": [
				0,
				0,
				1,
				0.111,
				0,
				0.222,
				0.3,
				0.333,
				0.3,
				1,
				0.722,
				0.3,
				1.111,
				0,
				1.5,
				0,
				1,
				1.644,
				0,
				1.789,
				0.3,
				1.933,
				0.3,
				1,
				2.6,
				0.3,
				3.267,
				0.3,
				3.933,
				0.3,
				1,
				4.178,
				0.3,
				4.422,
				0,
				4.667,
				0
			]
		},
		{
			"Target": "Parameter",
			"Id": "ParamBrowRAngle",
			"Segments": [
				0,
				0,
				1,
				0.111,
				0,
				0.222,
				0.3,
				0.333,
				0.3,
				1,
				0.722,
				0.3,
				1.111,
				0,
				1.5,
				0,
				1,
				1.644,
				0,
				1.789,
				0.3,
				1.933,
				0.3,
				1,
				2.6,
				0.3,
				3.267,
				0.3,
				3.933,
				0.3,
				1,
				4.178,
				0.3,
				4.422,
				0,
				4.667,
				0
			]
		},
		{
			"Target": "Parameter",
			"Id": "ParamBrowLForm",
			"Segments": [
				0,
				0,
				1,
				0.111,
				0,
				0.222,
				0.5,
				0.333,
				0.5,
				1,
				0.722,
				0.5,
				1.111,
				0,
				1.5,
				0,
				1,
				2.556,
				0,
				3.611,
				0,
				4.667,
				0
			]
		},
		{
			"Target": "Parameter",
			"Id": "ParamBrowRForm",
			"Segments": [
				0,
				0,
				1,
				0.111,
				0,
				0.222,
				0.5,
				0.333,
				0.5,
				1,
				0.722,
				0.5,
				1.111,
				0,
				1.5,
				0,
				1,
				2.556,
				0,
				3.611,
				0,
				4.667,
				0
			]
		},
		{
			"Target": "Parameter",
			"Id": "Param33",
			"Segments": [
				0,
				0,
				1,
				1.556,
				0,
				3.111,
				0,
				4.667,
				0
			]
		},
		{
			"Target": "Parameter",
			"Id": "Param32",
			"Segments": [
				0,
				0,
				1,
				1.556,
				0,
				3.111,
				0,
				4.667,
				0
			]
		},
		{
			"Target": "Parameter",
			"Id": "ParamMouthForm",
			"Segments": [
				0,
				0,
				1,
				1.333,
				0,
				2.667,
				-0.5,
				4,
				-0.5,
				1,
				4.222,
				-0.5,
				4.444,
				0,
				4.667,
				0
			]
		},
		{
			"Target": "Parameter",
			"Id": "ParamMouthOpenY",
			"Segments": [
				0,
				0,
				1,
				0.133,
				0,
				0.267,
				0.5,
				0.4,
				0.5,
				1,
				0.6,
				0.5,
				0.8,
				0.5,
				1,
				0.5,
				1,
				1.278,
				0.5,
				1.556,
				0,
				1.833,
				0,
				1,
				2.778,
				0,
				3.722,
				0,
				4.667,
				0
			]
		},
		{
			"Target": "Parameter",
			"Id": "Param4",
			"Segments": [
				0,
				0,
				1,
				1.556,
				0,
				3.111,
				0,
				4.667,
				0
			]
		},
		{
			"Target": "Parameter",
			"Id": "Param5",
			"Segments": [
				0,
				0,
				1,
				1.556,
				0,
				3.111,
				0,
				4.667,
				0
			]
		},
		{
			"Target": "Parameter",
			"Id": "ParamCheek",
			"Segments": [
				0,
				0,
				1,
				0.578,
				0,
				1.156,
				0,
				1.733,
				0,
				1,
				2.122,
				0,
				2.511,
				1,
				2.9,
				1,
				1,
				3.211,
				1,
				3.522,
				1,
				3.833,
				1,
				1,
				4,
				1,
				4.167,
				0,
				4.333,
				0,
				0,
				4.667,
				0
			]
		},
		{
			"Target": "Parameter",
			"Id": "Param34",
			"Segments": [
				0,
				0,
				1,
				1.444,
				0,
				2.889,
				0,
				4.333,
				0,
				0,
				4.667,
				0
			]
		},
		{
			"Target": "Parameter",
			"Id": "Param35",
			"Segments": [
				0,
				0,
				1,
				1.444,
				0,
				2.889,
				0,
				4.333,
				0,
				0,
				4.667,
				0
			]
		},
		{
			"Target": "Parameter",
			"Id": "Param36",
			"Segments": [
				0,
				0,
				1,
				1.444,
				0,
				2.889,
				0,
				4.333,
				0,
				0,
				4.667,
				0
			]
		},
		{
			"Target": "Parameter",
			"Id": "Param37",
			"Segments": [
				0,
				0,
				1,
				1.444,
				0,
				2.889,
				0,
				4.333,
				0,
				0,
				4.667,
				0
			]
		},
		{
			"Target": "Parameter",
			"Id": "Param39",
			"Segments": [
				0,
				-1,
				1,
				1.444,
				-1,
				2.889,
				-1,
				4.333,
				-1,
				0,
				4.667,
				-1
			]
		},
		{
			"Target": "Parameter",
			"Id": "Param30",
			"Segments": [
				0,
				0,
				1,
				0.078,
				0,
				0.156,
				0,
				0.233,
				0,
				1,
				0.311,
				0,
				0.389,
				0.5,
				0.467,
				0.5,
				1,
				0.522,
				0.5,
				0.578,
				0,
				0.633,
				0,
				1,
				1.867,
				0,
				3.1,
				0,
				4.333,
				0,
				0,
				4.667,
				0
			]
		},
		{
			"Target": "Parameter",
			"Id": "Param31",
			"Segments": [
				0,
				0,
				1,
				1.444,
				0,
				2.889,
				0,
				4.333,
				0,
				0,
				4.667,
				0
			]
		},
		{
			"Target": "Parameter",
			"Id": "Param29",
			"Segments": [
				0,
				0,
				1,
				1.522,
				0,
				3.044,
				0,
				4.567,
				0,
				0,
				4.667,
				0
			]
		},
		{
			"Target": "Parameter",
			"Id": "Param28",
			"Segments": [
				0,
				0,
				1,
				1.522,
				0,
				3.044,
				0,
				4.567,
				0,
				0,
				4.667,
				0
			]
		},
		{
			"Target": "Parameter",
			"Id": "Param26",
			"Segments": [
				0,
				0,
				1,
				0.511,
				0,
				1.022,
				0,
				1.533,
				0,
				1,
				1.678,
				0,
				1.822,
				-0.1,
				1.967,
				-0.1,
				1,
				2.178,
				-0.1,
				2.389,
				0,
				2.6,
				0,
				1,
				3.256,
				0,
				3.911,
				0,
				4.567,
				0,
				0,
				4.667,
				0
			]
		},
		{
			"Target": "Parameter",
			"Id": "Param27",
			"Segments": [
				0,
				0,
				1,
				0.022,
				0,
				0.044,
				0,
				0.067,
				0,
				1,
				0.144,
				0,
				0.222,
				0.2,
				0.3,
				0.2,
				1,
				0.367,
				0.2,
				0.433,
				0,
				0.5,
				0,
				1,
				0.844,
				0,
				1.189,
				0,
				1.533,
				0,
				1,
				1.822,
				0,
				2.111,
				-0.1,
				2.4,
				-0.1,
				1,
				2.811,
				-0.1,
				3.222,
				-0.1,
				3.633,
				-0.1,
				1,
				3.944,
				-0.1,
				4.256,
				0,
				4.567,
				0,
				0,
				4.667,
				0
			]
		},
		{
			"Target": "Parameter",
			"Id": "ParamBreath",
			"Segments": [
				0,
				0.034,
				1,
				1.522,
				0.034,
				3.044,
				0.034,
				4.567,
				0.034,
				0,
				4.667,
				0.034
			]
		},
		{
			"Target": "Parameter",
			"Id": "ParamLookBodyAngleX",
			"Segments": [
				0,
				0,
				1,
				0.022,
				0,
				0.044,
				0,
				0.067,
				0,
				1,
				0.144,
				0,
				0.222,
				1,
				0.3,
				1,
				1,
				0.389,
				1,
				0.478,
				0,
				0.567,
				0,
				1,
				0.889,
				0,
				1.211,
				0,
				1.533,
				0,
				1,
				1.678,
				0,
				1.822,
				4,
				1.967,
				4,
				1,
				2.178,
				4,
				2.389,
				0,
				2.6,
				0,
				1,
				3.256,
				0,
				3.911,
				0,
				4.567,
				0,
				0,
				4.667,
				0
			]
		},
		{
			"Target": "Parameter",
			"Id": "ParamLookBodyAngleY",
			"Segments": [
				0,
				0,
				1,
				0.011,
				0,
				0.022,
				0,
				0.033,
				0,
				1,
				0.111,
				0,
				0.189,
				1,
				0.267,
				1,
				1,
				0.356,
				1,
				0.444,
				0,
				0.533,
				0,
				1,
				0.867,
				0,
				1.2,
				0,
				1.533,
				0,
				1,
				1.822,
				0,
				2.111,
				-6,
				2.4,
				-6,
				1,
				2.644,
				-6,
				2.889,
				-4,
				3.133,
				-4,
				1,
				3.3,
				-4,
				3.467,
				-4,
				3.633,
				-4,
				1,
				3.944,
				-4,
				4.256,
				0,
				4.567,
				0,
				0,
				4.667,
				0
			]
		},
		{
			"Target": "Parameter",
			"Id": "ParamBodyAngleZ",
			"Segments": [
				0,
				0.069,
				1,
				1.522,
				0.069,
				3.044,
				0.069,
				4.567,
				0.069,
				0,
				4.667,
				0.069
			]
		},
		{
			"Target": "Parameter",
			"Id": "Param7",
			"Segments": [
				0,
				0.1,
				1,
				0.078,
				0.1,
				0.156,
				0.031,
				0.233,
				0,
				1,
				0.433,
				-0.08,
				0.633,
				-0.1,
				0.833,
				-0.1,
				1,
				1.067,
				-0.1,
				1.3,
				0.1,
				1.533,
				0.1,
				1,
				1.678,
				0.1,
				1.822,
				-0.3,
				1.967,
				-0.3,
				1,
				2.178,
				-0.3,
				2.389,
				0,
				2.6,
				0,
				1,
				2.878,
				0,
				3.156,
				-0.078,
				3.433,
				-0.078,
				1,
				3.478,
				-0.078,
				3.522,
				-0.078,
				3.567,
				-0.078,
				1,
				3.878,
				-0.078,
				4.189,
				0.1,
				4.5,
				0.1,
				0,
				4.667,
				0.1
			]
		},
		{
			"Target": "Parameter",
			"Id": "Param6",
			"Segments": [
				0,
				0,
				1,
				0.078,
				0,
				0.156,
				0.2,
				0.233,
				0.2,
				1,
				0.311,
				0.2,
				0.389,
				0,
				0.467,
				0,
				1,
				0.967,
				0,
				1.467,
				0,
				1.967,
				0,
				1,
				2.111,
				0,
				2.256,
				0.3,
				2.4,
				0.3,
				1,
				2.789,
				0.3,
				3.178,
				0.3,
				3.567,
				0.3,
				1,
				3.878,
				0.3,
				4.189,
				0,
				4.5,
				0,
				0,
				4.667,
				0
			]
		},
		{
			"Target": "Parameter",
			"Id": "Param8",
			"Segments": [
				0,
				0,
				1,
				1.5,
				0,
				3,
				0,
				4.5,
				0,
				0,
				4.667,
				0
			]
		},
		{
			"Target": "Parameter",
			"Id": "Param54",
			"Segments": [
				0,
				0,
				1,
				1.422,
				0,
				2.844,
				0,
				4.267,
				0,
				0,
				4.667,
				0
			]
		},
		{
			"Target": "Parameter",
			"Id": "Param43",
			"Segments": [
				0,
				0,
				1,
				0.811,
				0,
				1.622,
				0,
				2.433,
				0,
				1,
				2.444,
				0,
				2.456,
				0.3,
				2.467,
				0.3,
				1,
				2.9,
				0.3,
				3.333,
				0.3,
				3.767,
				0.3,
				1,
				3.778,
				0.3,
				3.789,
				0,
				3.8,
				0,
				0,
				4.667,
				0
			]
		},
		{
			"Target": "Parameter",
			"Id": "Param22",
			"Segments": [
				0,
				0,
				1,
				0.667,
				0,
				1.333,
				0,
				2,
				0,
				1,
				2.278,
				0,
				2.556,
				0.5,
				2.833,
				0.5,
				1,
				3.022,
				0.5,
				3.211,
				0.5,
				3.4,
				0.5,
				1,
				3.711,
				0.5,
				4.022,
				0,
				4.333,
				0,
				0,
				4.667,
				0
			]
		},
		{
			"Target": "Parameter",
			"Id": "Param21",
			"Segments": [
				0,
				0,
				1,
				1.467,
				0,
				2.933,
				0,
				4.4,
				0,
				0,
				4.667,
				0
			]
		},
		{
			"Target": "Parameter",
			"Id": "Param10",
			"Segments": [
				0,
				0,
				1,
				0.044,
				0,
				0.089,
				0,
				0.133,
				0,
				1,
				0.2,
				0,
				0.267,
				0.8,
				0.333,
				0.8,
				1,
				0.4,
				0.8,
				0.467,
				0,
				0.533,
				0,
				1,
				0.6,
				0,
				0.667,
				0.4,
				0.733,
				0.4,
				1,
				0.822,
				0.4,
				0.911,
				0.4,
				1,
				0.4,
				1,
				1.178,
				0.4,
				1.356,
				0,
				1.533,
				0,
				1,
				1.667,
				0,
				1.8,
				0,
				1.933,
				0,
				1,
				2.211,
				0,
				2.489,
				1,
				2.767,
				1,
				1,
				2.956,
				1,
				3.144,
				1,
				3.333,
				1,
				1,
				3.644,
				1,
				3.956,
				0,
				4.267,
				0,
				0,
				4.667,
				0
			]
		},
		{
			"Target": "Parameter",
			"Id": "Param11",
			"Segments": [
				0,
				0.003,
				1,
				0.533,
				0.003,
				1.067,
				0.003,
				1.6,
				0.003,
				1,
				1.733,
				0.003,
				1.867,
				-0.2,
				2,
				-0.2,
				1,
				2.278,
				-0.2,
				2.556,
				0.5,
				2.833,
				0.5,
				1,
				3.022,
				0.5,
				3.211,
				0.5,
				3.4,
				0.5,
				1,
				3.711,
				0.5,
				4.022,
				0.003,
				4.333,
				0.003,
				0,
				4.667,
				0.003
			]
		},
		{
			"Target": "Parameter",
			"Id": "Param9",
			"Segments": [
				0,
				0.002,
				1,
				0.1,
				0.002,
				0.2,
				0.044,
				0.3,
				0.044,
				1,
				0.367,
				0.044,
				0.433,
				0,
				0.5,
				0,
				1,
				0.9,
				0,
				1.3,
				0,
				1.7,
				0.002,
				1,
				1.833,
				0.003,
				1.967,
				0.2,
				2.1,
				0.2,
				1,
				2.378,
				0.2,
				2.656,
				0,
				2.933,
				0,
				1,
				3.111,
				0,
				3.289,
				0,
				3.467,
				0,
				1,
				3.622,
				0,
				3.778,
				-0.152,
				3.933,
				-0.152,
				1,
				4.089,
				-0.152,
				4.244,
				0.002,
				4.4,
				0.002,
				0,
				4.667,
				0.002
			]
		},
		{
			"Target": "Parameter",
			"Id": "Param14",
			"Segments": [
				0,
				-0.026,
				1,
				0.011,
				-0.026,
				0.022,
				-0.026,
				0.033,
				-0.026,
				1,
				0.133,
				-0.026,
				0.233,
				0.2,
				0.333,
				0.2,
				1,
				0.4,
				0.2,
				0.467,
				0.003,
				0.533,
				0,
				1,
				0.944,
				-0.02,
				1.356,
				-0.026,
				1.767,
				-0.026,
				1,
				1.833,
				-0.026,
				1.9,
				0.2,
				1.967,
				0.2,
				1,
				2.033,
				0.2,
				2.1,
				0,
				2.167,
				0,
				1,
				2.256,
				0,
				2.344,
				0,
				2.433,
				0,
				1,
				2.444,
				0,
				2.456,
				-0.5,
				2.467,
				-0.5,
				1,
				2.644,
				-0.5,
				2.822,
				0.5,
				3,
				0.5,
				1,
				3.178,
				0.5,
				3.356,
				0.487,
				3.533,
				0.4,
				1,
				3.611,
				0.362,
				3.689,
				0.2,
				3.767,
				0.2,
				1,
				3.778,
				0.2,
				3.789,
				0.2,
				3.8,
				0.2,
				1,
				4.022,
				0.2,
				4.244,
				-0.026,
				4.467,
				-0.026,
				0,
				4.667,
				-0.026
			]
		},
		{
			"Target": "Parameter",
			"Id": "Param15",
			"Segments": [
				0,
				0.208,
				1,
				1.444,
				0.208,
				2.889,
				0.208,
				4.333,
				0.208,
				0,
				4.667,
				0.208
			]
		},
		{
			"Target": "Parameter",
			"Id": "Param42",
			"Segments": [
				0,
				0,
				1,
				1.444,
				0,
				2.889,
				0,
				4.333,
				0,
				0,
				4.667,
				0
			]
		},
		{
			"Target": "Parameter",
			"Id": "Param40",
			"Segments": [
				0,
				0,
				1,
				1.444,
				0,
				2.889,
				0,
				4.333,
				0,
				0,
				4.667,
				0
			]
		},
		{
			"Target": "Parameter",
			"Id": "Param41",
			"Segments": [
				0,
				0,
				1,
				1.444,
				0,
				2.889,
				0,
				4.333,
				0,
				0,
				4.667,
				0
			]
		},
		{
			"Target": "Parameter",
			"Id": "Param47",
			"Segments": [
				0,
				0,
				1,
				1.5,
				0,
				3,
				0,
				4.5,
				0,
				0,
				4.667,
				0
			]
		},
		{
			"Target": "Parameter",
			"Id": "Param44",
			"Segments": [
				0,
				0,
				1,
				0.644,
				0,
				1.289,
				0,
				1.933,
				0,
				1,
				1.944,
				0,
				1.956,
				-1,
				1.967,
				-1,
				1,
				2.667,
				-1,
				3.367,
				-1,
				4.067,
				-1,
				1,
				4.078,
				-1,
				4.089,
				0,
				4.1,
				0,
				0,
				4.667,
				0
			]
		},
		{
			"Target": "Parameter",
			"Id": "Param23",
			"Segments": [
				0,
				0,
				1,
				0.511,
				0,
				1.022,
				0,
				1.533,
				0,
				1,
				1.767,
				0,
				2,
				0.5,
				2.233,
				0.5,
				1,
				2.678,
				0.5,
				3.122,
				0.5,
				3.567,
				0.5,
				1,
				3.878,
				0.5,
				4.189,
				0,
				4.5,
				0,
				0,
				4.667,
				0
			]
		},
		{
			"Target": "Parameter",
			"Id": "Param24",
			"Segments": [
				0,
				0,
				1,
				0.511,
				0,
				1.022,
				0,
				1.533,
				0,
				1,
				1.8,
				0,
				2.067,
				0.2,
				2.333,
				0.2,
				1,
				2.767,
				0.2,
				3.2,
				0.2,
				3.633,
				0.2,
				1,
				3.756,
				0.2,
				3.878,
				0.3,
				4,
				0.3,
				1,
				4.189,
				0.3,
				4.378,
				0,
				4.567,
				0,
				0,
				4.667,
				0
			]
		},
		{
			"Target": "Parameter",
			"Id": "Param12",
			"Segments": [
				0,
				0.063,
				1,
				0.044,
				0.063,
				0.089,
				0,
				0.133,
				0,
				1,
				0.2,
				0,
				0.267,
				0.8,
				0.333,
				0.8,
				1,
				0.4,
				0.8,
				0.467,
				0,
				0.533,
				0,
				1,
				0.6,
				0,
				0.667,
				0.4,
				0.733,
				0.4,
				1,
				1,
				0.4,
				1.267,
				0.063,
				1.533,
				0.063,
				1,
				1.744,
				0.063,
				1.956,
				1,
				2.167,
				1,
				1,
				2.611,
				1,
				3.056,
				1,
				3.5,
				1,
				1,
				3.811,
				1,
				4.122,
				0.063,
				4.433,
				0.063,
				0,
				4.667,
				0.063
			]
		},
		{
			"Target": "Parameter",
			"Id": "Param13",
			"Segments": [
				0,
				0.003,
				1,
				0.511,
				0.003,
				1.022,
				0.003,
				1.533,
				0.003,
				1,
				1.767,
				0.003,
				2,
				-0.3,
				2.233,
				-0.3,
				1,
				2.678,
				-0.3,
				3.122,
				-0.3,
				3.567,
				-0.3,
				1,
				3.878,
				-0.3,
				4.189,
				0.003,
				4.5,
				0.003,
				0,
				4.667,
				0.003
			]
		},
		{
			"Target": "Parameter",
			"Id": "Param16",
			"Segments": [
				0,
				0,
				1,
				0.056,
				0,
				0.111,
				0,
				0.167,
				0,
				1,
				0.233,
				0,
				0.3,
				-0.056,
				0.367,
				-0.056,
				1,
				0.756,
				-0.056,
				1.144,
				0,
				1.533,
				0,
				1,
				1.8,
				0,
				2.067,
				-0.1,
				2.333,
				-0.1,
				1,
				2.767,
				-0.1,
				3.2,
				-0.1,
				3.633,
				-0.1,
				1,
				3.944,
				-0.1,
				4.256,
				0,
				4.567,
				0,
				0,
				4.667,
				0
			]
		},
		{
			"Target": "Parameter",
			"Id": "Param17",
			"Segments": [
				0,
				0,
				1,
				0.067,
				0,
				0.133,
				0,
				0.2,
				0,
				1,
				0.267,
				0,
				0.333,
				-0.2,
				0.4,
				-0.2,
				1,
				0.467,
				-0.2,
				0.533,
				0,
				0.6,
				0,
				1,
				0.911,
				0,
				1.222,
				0,
				1.533,
				0,
				1,
				1.667,
				0,
				1.8,
				0.216,
				1.933,
				0.216,
				1,
				1.944,
				0.216,
				1.956,
				-1,
				1.967,
				-1,
				1,
				2.111,
				-1,
				2.256,
				0.5,
				2.4,
				0.5,
				1,
				2.833,
				0.5,
				3.267,
				0.5,
				3.7,
				0.5,
				1,
				3.822,
				0.5,
				3.944,
				0.389,
				4.067,
				0.389,
				1,
				4.078,
				0.389,
				4.089,
				1,
				4.1,
				1,
				1,
				4.278,
				1,
				4.456,
				0,
				4.633,
				0,
				0,
				4.667,
				0
			]
		},
		{
			"Target": "Parameter",
			"Id": "Param18",
			"Segments": [
				0,
				0,
				1,
				0.078,
				0,
				0.156,
				0,
				0.233,
				0,
				1,
				0.3,
				0,
				0.367,
				-0.5,
				0.433,
				-0.5,
				1,
				0.5,
				-0.5,
				0.567,
				0,
				0.633,
				0,
				1,
				1.922,
				0,
				3.211,
				0,
				4.5,
				0,
				0,
				4.667,
				0
			]
		},
		{
			"Target": "Parameter",
			"Id": "Param48",
			"Segments": [
				0,
				0,
				1,
				1.5,
				0,
				3,
				0,
				4.5,
				0,
				0,
				4.667,
				0
			]
		},
		{
			"Target": "Parameter",
			"Id": "Param50",
			"Segments": [
				0,
				0,
				1,
				0.511,
				0,
				1.022,
				0,
				1.533,
				0,
				1,
				1.889,
				0,
				2.244,
				-1,
				2.6,
				-1,
				1,
				2.9,
				-1,
				3.2,
				-1,
				3.5,
				-1,
				1,
				3.833,
				-1,
				4.167,
				0,
				4.5,
				0,
				0,
				4.667,
				0
			]
		},
		{
			"Target": "Parameter",
			"Id": "Param51",
			"Segments": [
				0,
				0,
				1,
				0.511,
				0,
				1.022,
				0,
				1.533,
				0,
				1,
				1.889,
				0,
				2.244,
				-0.9,
				2.6,
				-0.9,
				1,
				2.9,
				-0.9,
				3.2,
				-0.9,
				3.5,
				-0.9,
				1,
				3.833,
				-0.9,
				4.167,
				0,
				4.5,
				0,
				0,
				4.667,
				0
			]
		},
		{
			"Target": "Parameter",
			"Id": "Param52",
			"Segments": [
				0,
				0,
				1,
				0.511,
				0,
				1.022,
				0,
				1.533,
				0,
				1,
				1.889,
				0,
				2.244,
				0.8,
				2.6,
				0.8,
				1,
				2.9,
				0.8,
				3.2,
				0.8,
				3.5,
				0.8,
				1,
				3.833,
				0.8,
				4.167,
				0,
				4.5,
				0,
				0,
				4.667,
				0
			]
		},
		{
			"Target": "Parameter",
			"Id": "Param49",
			"Segments": [
				0,
				0,
				1,
				1.167,
				0,
				2.333,
				0,
				3.5,
				0,
				1,
				3.833,
				0,
				4.167,
				0,
				4.5,
				0,
				0,
				4.667,
				0
			]
		},
		{
			"Target": "Parameter",
			"Id": "Param19",
			"Segments": [
				0,
				0,
				1,
				0.511,
				0,
				1.022,
				0,
				1.533,
				0,
				1,
				1.733,
				0,
				1.933,
				1,
				2.133,
				1,
				1,
				2.778,
				1,
				3.422,
				1,
				4.067,
				1,
				1,
				4.267,
				1,
				4.467,
				0,
				4.667,
				0
			]
		},
		{
			"Target": "Parameter",
			"Id": "Param20",
			"Segments": [
				0,
				0,
				1,
				0.511,
				0,
				1.022,
				0,
				1.533,
				0,
				1,
				1.8,
				0,
				2.067,
				1,
				2.333,
				1,
				1,
				2.911,
				1,
				3.489,
				1,
				4.067,
				1,
				1,
				4.267,
				1,
				4.467,
				0,
				4.667,
				0
			]
		},
		{
			"Target": "Parameter",
			"Id": "Param45",
			"Segments": [
				0,
				0,
				1,
				1.556,
				0,
				3.111,
				0,
				4.667,
				0
			]
		},
		{
			"Target": "Parameter",
			"Id": "Param46",
			"Segments": [
				0,
				0,
				1,
				1.556,
				0,
				3.111,
				0,
				4.667,
				0
			]
		}
	]
}